Metadata-Version: 1.1
Name: peyotl
Version: 0.1.2
Summary: Library for interacting with Open Tree of Life resources
Home-page: https://github.com/OpenTreeOfLife/peyotl
Author: Emily Jane B. McTavish and Mark T. Holder
Author-email: UNKNOWN
License: BSD
Platform: UNKNOWN
Classifier: Development Status :: 1 - Planning
Classifier: Intended Audience :: Science/Research
Classifier: Intended Audience :: Developers
Classifier: Natural Language :: English
Classifier: License :: OSI Approved :: BSD License
Classifier: Operating System :: OS Independent
Classifier: Programming Language :: Python :: 2.7
Classifier: Topic :: Scientific/Engineering :: Bio-Informatics
